{
    "site_scripts_common": [
        {
            "url": "/view-resources/baseview/public/common/build/baseview_dependencies_dom.js",
            "requireDom": true,
            "attributes": [{
                "key": "data-cookieconsent",
                "value": "ignore"
            }]
        },
        {
            "url": "/view-resources/baseview/public/common/imageExpand.js",
            "requireDom": true
        },
        {
            "url": "/view-resources/baseview/public/common/ImageZoom.js",
            "requireDom": true,
            "pageType": "article"
        },
        {
            "url": "/view-resources/baseview/public/common/baseview/moduleHandlers.js",
            "isModule": true
        }
    ],
    "site_scripts": {
    }
}


